ShuaiToolBox/EORmodule.c
ShuaiToolBox/EORmodule.cp37-win_amd64.pyd
ShuaiToolBox/FindContours.c
ShuaiToolBox/FindContours.cp37-win_amd64.pyd
ShuaiToolBox/VideoPro.c
ShuaiToolBox/VideoPro.cp37-win_amd64.pyd
ShuaiToolBox/VideoProList.c
ShuaiToolBox/VideoProList.cp37-win_amd64.pyd
ShuaiToolBox/__init__.py
ShuaiToolBox/add.c
ShuaiToolBox/add.cp37-win_amd64.pyd
ShuaiToolBox/cv_plugin.c
ShuaiToolBox/cv_plugin.cp37-win_amd64.pyd
ShuaiToolBox/cv_vdopro.c
ShuaiToolBox/cv_vdopro.cp37-win_amd64.pyd
ShuaiToolBox/opencv_Functions.c
ShuaiToolBox/opencv_Functions.cp37-win_amd64.pyd
ShuaiToolBox/py_plugin.c
ShuaiToolBox/py_plugin.cp37-win_amd64.pyd
ShuaiToolBox/setup.c
ShuaiToolBox/setup.cp37-win_amd64.pyd
ShuaiToolBox/build/temp.win-amd64-3.7/Release/EORmodule.cp37-win_amd64.exp
ShuaiToolBox/build/temp.win-amd64-3.7/Release/EORmodule.cp37-win_amd64.lib
ShuaiToolBox/build/temp.win-amd64-3.7/Release/EORmodule.obj
ShuaiToolBox/build/temp.win-amd64-3.7/Release/FindContours.cp37-win_amd64.exp
ShuaiToolBox/build/temp.win-amd64-3.7/Release/FindContours.cp37-win_amd64.lib
ShuaiToolBox/build/temp.win-amd64-3.7/Release/FindContours.obj
ShuaiToolBox/build/temp.win-amd64-3.7/Release/VideoPro.cp37-win_amd64.exp
ShuaiToolBox/build/temp.win-amd64-3.7/Release/VideoPro.cp37-win_amd64.lib
ShuaiToolBox/build/temp.win-amd64-3.7/Release/VideoPro.obj
ShuaiToolBox/build/temp.win-amd64-3.7/Release/VideoProList.cp37-win_amd64.exp
ShuaiToolBox/build/temp.win-amd64-3.7/Release/VideoProList.cp37-win_amd64.lib
ShuaiToolBox/build/temp.win-amd64-3.7/Release/VideoProList.obj
ShuaiToolBox/build/temp.win-amd64-3.7/Release/add.cp37-win_amd64.exp
ShuaiToolBox/build/temp.win-amd64-3.7/Release/add.cp37-win_amd64.lib
ShuaiToolBox/build/temp.win-amd64-3.7/Release/add.obj
ShuaiToolBox/build/temp.win-amd64-3.7/Release/cv_plugin.cp37-win_amd64.exp
ShuaiToolBox/build/temp.win-amd64-3.7/Release/cv_plugin.cp37-win_amd64.lib
ShuaiToolBox/build/temp.win-amd64-3.7/Release/cv_plugin.obj
ShuaiToolBox-1.1.2.10.dist-info/METADATA
ShuaiToolBox-1.1.2.10.dist-info/WHEEL
ShuaiToolBox-1.1.2.10.dist-info/license.txt
ShuaiToolBox-1.1.2.10.dist-info/top_level.txt
ShuaiToolBox-1.1.2.10.dist-info/RECORD
