Metadata-Version: 2.1
Name: ShuaiToolBox
Version: 1.1.2.10
Summary: packages for experiments process
Home-page: UNKNOWN
Author: ShuaiZ
License: UNKNOWN
Platform: UNKNOWN
Requires-Python: >=3.7
Requires-Dist: numpy
Requires-Dist: natsort
Requires-Dist: opencv-python
